flax_weightwatcher/__init__.py
flax_weightwatcher/weightwatcher.py
flax_weightwatcher-0.1.1.dist-info/METADATA
flax_weightwatcher-0.1.1.dist-info/WHEEL
flax_weightwatcher-0.1.1.dist-info/top_level.txt
flax_weightwatcher-0.1.1.dist-info/RECORD
