Metadata-Version: 2.4
Name: flax-weightwatcher
Version: 0.1.1
Summary: A smaller, faster, cleaner WeightWatcher for FLAX/JAX with XLA
Home-page: https://github.com/jaisidhsingh/flax-weightwatcher
Author: Jaisidh Singh
Author-email: jaisidh.singh@student.uni-tuebingen.com
Requires-Python: >=3.12
Requires-Dist: flax>=0.12.0
Requires-Dist: jax>=0.7.2
Requires-Dist: jaxtyping>=0.3.3
Requires-Dist: numpy>=2.3.3
Requires-Dist: pandas>=2.3.3
Requires-Dist: powerlaw>=1.5
Dynamic: author
Dynamic: author-email
Dynamic: home-page
Dynamic: requires-python
